asgi_monitor/__init__.py
asgi_monitor/cli.py
asgi_monitor/py.typed
asgi_monitor/integrations/__init__.py
asgi_monitor/integrations/aiohttp.py
asgi_monitor/integrations/fastapi.py
asgi_monitor/integrations/litestar.py
asgi_monitor/integrations/starlette.py
asgi_monitor/logging/__init__.py
asgi_monitor/logging/_default_processors.py
asgi_monitor/logging/configure.py
asgi_monitor/logging/trace_processor.py
asgi_monitor/logging/aiohttp/__init__.py
asgi_monitor/logging/aiohttp/logger.py
asgi_monitor/logging/gunicorn/__init__.py
asgi_monitor/logging/gunicorn/logger.py
asgi_monitor/logging/gunicorn/worker.py
asgi_monitor/logging/uvicorn/__init__.py
asgi_monitor/logging/uvicorn/log_config.py
asgi_monitor/logging/uvicorn/worker.py
asgi_monitor/metrics/__init__.py
asgi_monitor/metrics/config.py
asgi_monitor/metrics/container.py
asgi_monitor/metrics/get_latest.py
asgi_monitor/metrics/manager.py
asgi_monitor/tracing/__init__.py
asgi_monitor/tracing/config.py
asgi_monitor/tracing/decorator.py
asgi_monitor/tracing/middleware.py
asgi_monitor-0.6.1.dist-info/licenses/LICENSE
asgi_monitor-0.6.1.dist-info/METADATA
asgi_monitor-0.6.1.dist-info/WHEEL
asgi_monitor-0.6.1.dist-info/entry_points.txt
asgi_monitor-0.6.1.dist-info/top_level.txt
asgi_monitor-0.6.1.dist-info/RECORD
