Metadata-Version: 2.4
Name: asgi-monitor
Version: 0.6.1
Summary: Quick and easy monitoring setup for ASGI application
Author-email: treaditup <treaditup@gmail.com>
License: MIT
Project-URL: Documentation, https://asgi-monitor.readthedocs.io
Project-URL: Source, https://github.com/draincoder/asgi-monitor
Project-URL: Homepage, https://github.com/draincoder/asgi-monitor
Project-URL: Bug Tracker, https://github.com/draincoder/asgi-monitor/issues
Classifier: Programming Language :: Python :: 3.10
Classifier: Programming Language :: Python :: 3.11
Classifier: Programming Language :: Python :: 3.12
Classifier: Topic :: Software Development :: Libraries
Classifier: Typing :: Typed
Classifier: Intended Audience :: Developers
Classifier: License :: OSI Approved :: MIT License
Classifier: Operating System :: OS Independent
Requires-Python: >=3.10
License-File: LICENSE
Requires-Dist: structlog>=24.1.0
Requires-Dist: prometheus-client>=0.20.0
Requires-Dist: opentelemetry-sdk>=1.23.0
Requires-Dist: opentelemetry-instrumentation-asgi>=0.44b0
Requires-Dist: click>=8.1.7
Dynamic: license-file
